<?xml version="1.0" encoding="utf-8"?>
<jni4net-proxygen xmlns:xsi="http://www.w3.org/2001/XMLSchema-instance" xmlns:xsd="http://www.w3.org/2001/XMLSchema" xmlns="http://jni4net.sf.net/0.8.6.0/toolConfig.xsd">
  <TargetDirJvm>java</TargetDirJvm>
  <TargetDirClr>clr</TargetDirClr>
  <ClassPath Path="lib/compiler.jar" />
  <JavaClass TypeName="com.google.javascript.jscomp.JSError" />
  <JavaClass TypeName="com.google.javascript.jscomp.Result" />
  <JavaClass TypeName="com.google.javascript.jscomp.JSSourceFile" />
  <JavaClass TypeName="com.google.javascript.jscomp.SourceFile" />
  <JavaClass TypeName="com.google.javascript.jscomp.Compiler" />
  <JavaClass TypeName="com.google.javascript.jscomp.CompilerOptions" />
  <JavaClass TypeName="com.google.javascript.jscomp.CompilationLevel" />
  <JavaClass TypeName="com.google.javascript.jscomp.WarningLevel" />
  <JavaClass TypeName="com.google.javascript.jscomp.CheckLevel" />
  <JavaClass TypeName="com.google.javascript.jscomp.DiagnosticGroups" />
  <JavaClass TypeName="com.google.javascript.jscomp.CommandLineRunner" />
</jni4net-proxygen>